pkgbuild_parser/__init__.py
pkgbuild_parser/parser_core.py
pkgbuild_parser/pkgbuild_parser.py
pkgbuild_parser-1.0.1.dist-info/licenses/LICENSE
pkgbuild_parser-1.0.1.dist-info/METADATA
pkgbuild_parser-1.0.1.dist-info/WHEEL
pkgbuild_parser-1.0.1.dist-info/top_level.txt
pkgbuild_parser-1.0.1.dist-info/RECORD
