Metadata-Version: 2.4
Name: pkgbuild-parser
Version: 1.0.1
Summary: Simple Python module to extract basic information directly from PKGBUILD files (not .SRCINFO)
Author: KevinCrrl
License: MIT
Project-URL: Homepage, https://github.com/KevinCrrl/pkgbuild_parser
Requires-Python: >=3.10
License-File: LICENSE
Dynamic: license-file
